{"stem":"académiqu","instances":[{"docId":"melloni-an-littrow-1854-a3-xxi-d314","docUri":"melloni-an-littrow-1854-a3-xxi-d314.html","score":2,"contexts":[{"form":"académique","weight":"1","pos":1045,"context":"...la plus heureuse influence. Embouchez donc la trompette <mark>académique<\/mark>, Monsieur et cher collègue, et soufflez dedans...","fid":"d430e216"},{"form":"académiques","weight":"1","pos":1558,"context":"...Thermochrôse en prenant une part fort active aux influences <mark>académiques<\/mark> qui me procurèrent la tranquillité et les moyens nécessaires...","fid":"d430e282"}]}]}