{"stem":"ano","instances":[{"docId":"rojek-an-thun-1854-11-14-a3-xxi-d302","docUri":"rojek-an-thun-1854-11-14-a3-xxi-d302.html","score":9,"contexts":[{"form":"ano","weight":"1","pos":290,"context":"...kříže záslužního představenému zdejšího města oslaviti kostelní pobožností – <mark>ano<\/mark> i povedlo se jemu většinu sousedstva zdejšího slovy svými...","fid":"d570e129"},{"form":"ano","weight":"1","pos":544,"context":"...: Chrám jest příbytek andělů, brána nebeská, <mark>ano<\/mark> – nebe samo. Sv. Nilus pak: Považuj...","fid":"d570e166"},{"form":"ano","weight":"1","pos":1401,"context":"...Ap. 5– ale tělo své volně vydávali mukám, <mark>ano<\/mark> i radovali se a díky vzdávali Bohu, že...","fid":"d570e166"},{"form":"ano","weight":"1","pos":1507,"context":"..., ostrovy, hrady, pevnosti, sbory. <mark>ano<\/mark> i tábory, … palác císařský, senát a...","fid":"d570e166"},{"form":"ano","weight":"1","pos":1810,"context":"...přináší starosti a péči o dobro svých zemí, <mark>ano<\/mark> i noční doby obětuje, chtě tak řka sám...","fid":"d570e166"},{"form":"ano","weight":"1","pos":2524,"context":"...života – zponenáhla zobecněla ve vyšších společnostech Francouzska – <mark>ano<\/mark> i při samém dvoře královském. – Nákaza ta,...","fid":"d570e166"},{"form":"Ano","weight":"1","pos":2799,"context":"...kteříž byli před námi. Eccles 1.1. – <mark>Ano<\/mark>, nic nového pod sluncem! – nic,...","fid":"d570e166"},{"form":"ano","weight":"1","pos":3279,"context":"..., a po něm v běhu téhož času kleslo <mark>ano<\/mark> i v nepaměť padlo nejedno slavné a mocné království...","fid":"d570e166"},{"form":"ano","weight":"1","pos":3898,"context":"...vaše do minulých časů chvalnou mělo pověst, – <mark>ano<\/mark> že považováno bývalo za jedno z nejpřednějších po celém...","fid":"d570e166"}]}]}