{"stem":"anonimo","instances":[{"docId":"debiasi-an-thun-1854-06-22-a3-xxi-d263","docUri":"debiasi-an-thun-1854-06-22-a3-xxi-d263.html","score":3,"contexts":[{"form":"Anonimo","weight":"1","pos":1232,"context":"...il suo attaccamento al Regnante. Nel seguito un <mark>Anonimo<\/mark> da Innsbruck diede fuori un articolo col quale egli...","fid":"d104e187"},{"form":"Anonimo","weight":"1","pos":3000,"context":"...per ribattere una taccia, che immeritamente da un <mark>Anonimo<\/mark> di Innsbruck era stata scagliata anche contro quei Tirolesi...","fid":"d104e187"},{"form":"anonimo","weight":"1","pos":4367,"context":"Nell’articolo <mark>anonimo<\/mark> del Foglio N. 47 in questa Gazzetta scagliossi in...","fid":"d104e597"}]}]}