{"stem":"apoštol","instances":[{"docId":"rojek-an-thun-1854-11-14-a3-xxi-d302","docUri":"rojek-an-thun-1854-11-14-a3-xxi-d302.html","score":3,"contexts":[{"form":"apoštol","weight":"1","pos":689,"context":"...neuvěří, bude zatracen. Mar. 16– Sv. <mark>apoštol<\/mark> Pavel dokládá takto: My pak kážeme Krista ukřižovaného...","fid":"d570e166"},{"form":"apoštol","weight":"1","pos":1996,"context":"...svého – císaře apoštolského, který příkladem svým jako <mark>apoštol<\/mark> hlásá lidu zesvětštilému víru v Krista Ježíše, Syna...","fid":"d570e166"},{"form":"apoštol","weight":"1","pos":3482,"context":"...služebník dobrý plní vůli pána svého, jak velí <mark>apoštol<\/mark>. Služebníci, poslušni buďte ve všem pánů svých...","fid":"d570e166"}]}]}