{"stem":"aufmunternden","instances":[{"docId":"kuzmany-an-thun-1860-10-15-a3-xxi-d620","docUri":"kuzmany-an-thun-1860-10-15-a3-xxi-d620.html","score":1,"contexts":[{"form":"aufmunternden","weight":"1","pos":204,"context":"...je eher desorganisirt werden. Wie gegenüber solchen Kundgebungen die <mark>aufmunternden<\/mark> Worte Seiner Majestät, welche allerhöchst dieselben an die...","fid":"d380e111"}]},{"docId":"kleemann-an-thun-1858-06-23-a3-xxi-d456","docUri":"kleemann-an-thun-1858-06-23-a3-xxi-d456.html","score":1,"contexts":[{"form":"aufmunternden","weight":"1","pos":2259,"context":"...in meinen Erhebungen zu Gott stets den stärkenden, <mark>aufmunternden<\/mark> Trost, daß alles, auch Schlimmes, zum Besten...","fid":"d359e286"}]}]}