{"stem":"bergrath","instances":[{"docId":"hingenau-an-thun-1860-05-11-a3-xxi-d583","docUri":"hingenau-an-thun-1860-05-11-a3-xxi-d583.html","score":1,"contexts":[{"form":"Bergrath","weight":"1","pos":137,"context":"...; jeder der Hauptmitglieder der Reichsanstalt Hauer (beide, der <mark>Bergrath<\/mark> und der Chemiker), Fötterle, Stur u. a....","fid":"d290e105"}]},{"docId":"hingenau-an-thun-1860-06-20-a3-xxi-d593","docUri":"hingenau-an-thun-1860-06-20-a3-xxi-d593.html","score":1,"contexts":[{"form":"Bergrath","weight":"1","pos":131,"context":"...so wie jenes kleine Mémoire zu übersenden, welches <mark>Bergrath<\/mark> Fötterle, der einzige der noch anwesenden Geologen,...","fid":"d291e110"}]}]}