{"stem":"bude","instances":[{"docId":"rojek-an-thun-1854-11-14-a3-xxi-d302","docUri":"rojek-an-thun-1854-11-14-a3-xxi-d302.html","score":10,"contexts":[{"form":"bude","weight":"1","pos":672,"context":"...kažte Evangelium všemu stvoření. Kdo uvěří a pokřtěn <mark>bude<\/mark>, spasen bude, – Kdož pak neuvěří,...","fid":"d570e166"},{"form":"bude","weight":"1","pos":674,"context":"...stvoření. Kdo uvěří a pokřtěn bude, spasen <mark>bude<\/mark>, – Kdož pak neuvěří, bude zatracen....","fid":"d570e166"},{"form":"bude","weight":"1","pos":678,"context":"..., spasen bude, – Kdož pak neuvěří, <mark>bude<\/mark> zatracen. Mar. 16– Sv. apoštol Pavel dokládá...","fid":"d570e166"},{"form":"bude","weight":"1","pos":1213,"context":"...po všecky časy činila, až do skonání volati <mark>bude<\/mark> synům lidským slovy Krista a apoštolův: Dávejte,...","fid":"d570e166"},{"form":"bude","weight":"1","pos":2675,"context":"...veřejně se hlásalo, že jen tehdáž na zemi <mark>bude<\/mark> dobře když střevami posledního kněze zaškrcen bude král poslední...","fid":"d570e166"},{"form":"bude","weight":"1","pos":2682,"context":"...na zemi bude dobře když střevami posledního kněze zaškrcen <mark>bude<\/mark> král poslední!? – Jakého divu, když i...","fid":"d570e166"},{"form":"bude","weight":"1","pos":3606,"context":"...!!! – Proto věrný služebník císaře svého příkladem svým <mark>bude<\/mark> předcházeti a k tomu hleděti, aby sám Bohu...","fid":"d570e166"},{"form":"bude","weight":"1","pos":3626,"context":"..., že pak i císaři a pánu jeho ochotně <mark>bude<\/mark> dáno, co jest císařovo; – jinak nic...","fid":"d570e166"},{"form":"bude","weight":"1","pos":4013,"context":"...Víru a poslušnost. – Kdo věří, spasen <mark>bude<\/mark>: kdo nevěří bude zatracen, – tak praví...","fid":"d570e166"},{"form":"bude","weight":"1","pos":4016,"context":"...– Kdo věří, spasen bude: kdo nevěří <mark>bude<\/mark> zatracen, – tak praví Kristus Pán, amy...","fid":"d570e166"}]},{"docId":"tomek-an-thun-konzept-od-ca1407","docUri":"tomek-an-thun-konzept-od-ca1407.html","score":1,"contexts":[{"form":"bude","weight":"1","pos":173,"context":"...hotov byl; a však učiním, seč mne <mark>bude<\/mark>, odevzdávaje se přitom naději, že kdyby se...","fid":"d792e118"}]},{"docId":"amerling-an-thun-1853-07-20-a3-xxi-d217","docUri":"amerling-an-thun-1853-07-20-a3-xxi-d217.html","score":1,"contexts":[{"form":"bude","weight":"1","pos":147,"context":"...Prosím v hluboké pokoře opět o túže milost, <mark>bude<\/mark>-li nějaké místečko silám a schopnostem mým kdekoli v...","fid":"d15e118"}]},{"docId":"celakovsky-an-thun-1850-a3-xxi-d82","docUri":"celakovsky-an-thun-1850-a3-xxi-d82.html","score":1,"contexts":[{"form":"bude","weight":"1","pos":288,"context":"..., že i takto k pohodlné mé výživě postačovati <mark>bude<\/mark>. Leč poučen nyní nemilou zkušeností vidím, kterak...","fid":"d88e114"}]},{"docId":"korinek-an-thun-1853-a3-xxi-d247","docUri":"korinek-an-thun-1853-a3-xxi-d247.html","score":1,"contexts":[{"form":"bude","weight":"1","pos":116,"context":"..., kdo na šlechetné srdce Vaše appeluje, zdaliž <mark>bude<\/mark> odmrštěn? Tímto přesvědčením jsa veden, osmělil jsem...","fid":"d366e114"}]}]}