{"stem":"coloman","instances":[{"docId":"listperson","docUri":"listperson.html","score":1,"contexts":[{"form":"Coloman","weight":"1","pos":10770,"context":"<mark>Coloman<\/mark>","fid":"tocTable"}]},{"docId":"liechtenstein-an-thun-1851-10-03-a3-xxi-d124","docUri":"liechtenstein-an-thun-1851-10-03-a3-xxi-d124.html","score":1,"contexts":[{"form":"Coloman","weight":"1","pos":74,"context":"...hiermit anzuzeigen, daß ich diesen erledigten Stiftungsplatz dem <mark>Coloman<\/mark> von Tibolth, Sohn des k.k. Bezirkscommissairs in Eisenstadt...","fid":"d399e109"}]}]}