{"stem":"deutsch-nazionalen","instances":[{"docId":"thun-an-tomek-1854-05-12-ca993","docUri":"thun-an-tomek-1854-05-12-ca993.html","score":2,"contexts":[{"form":"deutsch-nazionalen","weight":"1","pos":215,"context":"...in Zweifel ziehen und uns mit anderen Gegnern der <mark>deutsch-nazionalen<\/mark> Partheien verwechseln könne. Die Gefahr dessen ist in...","fid":"d762e114"},{"form":"deutsch-nazionalen","weight":"1","pos":232,"context":"...von Leuten gehegt werden, die noch keineswegs zu jener <mark>deutsch-nazionalen<\/mark> Partei gehören. Ich bin nun in der That...","fid":"d762e114"}]}]}