{"stem":"fürstin","instances":[{"docId":"thun-an-unbekannt-1851-04-03-ca1207","docUri":"thun-an-unbekannt-1851-04-03-ca1207.html","score":2,"contexts":[{"form":"Fürstin","weight":"1","pos":77,"context":"Gnädige <mark>Fürstin<\/mark>! Ich freue mich Ihnen mittheilen zu können, daß...","fid":"d765e112"},{"form":"Fürstin","weight":"1","pos":144,"context":"...aufrichtiger Verehrung habe ich die Ehre zu verharren gnädige <mark>Fürstin<\/mark> Ihr ergebenster Diener","fid":"d765e112"}]},{"docId":"pauli-an-ministerium-fuer-kultus-und-unterricht-1851-04-05-a3-xxi-d111","docUri":"pauli-an-ministerium-fuer-kultus-und-unterricht-1851-04-05-a3-xxi-d111.html","score":1,"contexts":[{"form":"Fürstin","weight":"1","pos":809,"context":"..., dann als französischer Schreiber bei Ihrer Durchlaucht, <mark>Fürstin<\/mark> Salm, und später gab ich einige Stunden täglich...","fid":"d494e111"}]},{"docId":"listperson","docUri":"listperson.html","score":1,"contexts":[{"form":"Fürstin","weight":"1","pos":9047,"context":"<mark>Fürstin<\/mark> von Salm","fid":"tocTable"}]},{"docId":"simor-an-thun-1854-11-14-a3-xxi-d296b","docUri":"simor-an-thun-1854-11-14-a3-xxi-d296b.html","score":1,"contexts":[{"form":"Fürstin","weight":"1","pos":394,"context":"..., usw. usw. Die Hausfrau machte die <mark>Fürstin<\/mark> Odeschalchi, deren Mann im ungarischen Costum erschien....","fid":"d617e154"}]}]}