{"stem":"größtes","instances":[{"docId":"sammelakt-prozess-aigner-vs-ruben_1856_a3-xxi-d402","docUri":"sammelakt-prozess-aigner-vs-ruben_1856_a3-xxi-d402.html","score":1,"contexts":[{"form":"größtes","weight":"1","pos":3909,"context":"...entfernt gerechten Anlaß zu Tadel zu geben, sein <mark>größtes<\/mark> Verdienst und rechtfertigt mehr als alles andere die Wahl...","fid":"d577e1995"}]},{"docId":"rauscher-an-thun-1855-01-11-a3-xxi-d324","docUri":"rauscher-an-thun-1855-01-11-a3-xxi-d324.html","score":1,"contexts":[{"form":"größtes","weight":"1","pos":44,"context":"...bisher mehr Schwierigkeiten bereite als zunächst erwartet wurde. Als <mark>größtes<\/mark> Problem schildert Rauscher jedoch, dass der Fürstprimas von Ungarn...","fid":"d545e55"}]}]}