{"stem":"hauptstädten","instances":[{"docId":"bonitz-an-thun-1858-07-a3-xxi-d463","docUri":"bonitz-an-thun-1858-07-a3-xxi-d463.html","score":2,"contexts":[{"form":"Hauptstädten","weight":"1","pos":1078,"context":"...Grammaticallehrer) und 1200 fl (Humanitätslehrer), in <mark>Hauptstädten<\/mark> bis 1400 und 1600 fl erheben konnte.2 Mit...","fid":"d73e315"},{"form":"Hauptstädten","weight":"1","pos":1443,"context":"...Schuldgeld an Gymnasien, 12 fl jährlich in den <mark>Hauptstädten<\/mark> der Kronländer, 8 fl an den übrigen Orten...","fid":"d73e360"}]}]}