{"stem":"hausordnung","instances":[{"docId":"schwarzenberg-an-thun-1854-08-30-a3-xxi-d278","docUri":"schwarzenberg-an-thun-1854-08-30-a3-xxi-d278.html","score":1,"contexts":[{"form":"Hausordnung","weight":"1","pos":173,"context":"...Armuth, eine Hintanhaltung mancher Mißbräuche in der täglichen <mark>Hausordnung<\/mark> und dergleichen schwer und fast unmöglich wurde. Da eine...","fid":"d606e111"}]},{"docId":"weiss-an-thun-1855-08-06-a3-xxi-d347a","docUri":"weiss-an-thun-1855-08-06-a3-xxi-d347a.html","score":1,"contexts":[{"form":"Hausordnung","weight":"1","pos":1051,"context":"...lagen, wie ich später erfuhr, in der <mark>Hausordnung<\/mark>; eben erfahre ich, daß ein Curs im Priesterseminar...","fid":"d832e152"}]}]}