{"stem":"imponirend","instances":[{"docId":"moy-an-thun-1853-07-21-a3-xxi-d219","docUri":"moy-an-thun-1853-07-21-a3-xxi-d219.html","score":1,"contexts":[{"form":"imponirende","weight":"1","pos":245,"context":"...wissenschaftlichem Streben an, wenn auch am Orte nicht hinreichend <mark>imponirende<\/mark> Lehrkräfte vorhanden sind, um sie zu fesseln. Es...","fid":"d454e115"}]},{"docId":"weiss-an-thun-1855-08-06-a3-xxi-d347a","docUri":"weiss-an-thun-1855-08-06-a3-xxi-d347a.html","score":1,"contexts":[{"form":"imponirendes","weight":"1","pos":422,"context":"...Badenweiler und Baden-Baden zu. Bock besitzt ein <mark>imponirendes<\/mark> Wissen, von der Zeit von Augustus bis in das...","fid":"d832e152"}]}]}