{"stem":"impérieus","instances":[{"docId":"pitra-an-thun-1860-09-04-a3-xxi-d608","docUri":"pitra-an-thun-1860-09-04-a3-xxi-d608.html","score":1,"contexts":[{"form":"impérieusement","weight":"1","pos":1415,"context":"...Cyrille et de S. Méthode en 1863 semble ériger <mark>impérieusement<\/mark> que l'on vienne au plus tôt en aide aux...","fid":"d516e119"}]},{"docId":"melloni-an-littrow-1854-a3-xxi-d314","docUri":"melloni-an-littrow-1854-a3-xxi-d314.html","score":1,"contexts":[{"form":"impérieuse","weight":"1","pos":261,"context":"...en soit, j'obéis à l'invitation tant soit peu <mark>impérieuse<\/mark> du consul impérial en lui confiant deux exemplaires de...","fid":"d430e112"}]}]}