{"stem":"institutsdirekt","instances":[{"docId":"fuchs-an-thun-1853-04-08-a3-xxi-d198","docUri":"fuchs-an-thun-1853-04-08-a3-xxi-d198.html","score":2,"contexts":[{"form":"Institutsdirektion","weight":"1","pos":169,"context":"...zur Anschaffung von Modellen und die Aufforderung an die <mark>Institutsdirektion<\/mark> zur Ausmittlung eines geeigneten Lokale und Überreichung der Kostenüberschläge...","fid":"d205e115"},{"form":"Institutsdirektion","weight":"1","pos":178,"context":"...Überreichung der Kostenüberschläge. Im September 1852 legte die <mark>Institutsdirektion<\/mark> die Pläne und Kostenüberschläge für die Herrichtung einer ganz...","fid":"d205e115"}]}]}