{"stem":"justizgeschäften","instances":[{"docId":"entwurf-einrichtung-wirkungskreis-bezirksaemter_1852_a3-xxi-d85","docUri":"entwurf-einrichtung-wirkungskreis-bezirksaemter_1852_a3-xxi-d85.html","score":2,"contexts":[{"form":"Justizgeschäften","weight":"1","pos":303,"context":"...ausdrücklich anderen Behörden oder Organen vorbehaltenen Verwaltungs- und <mark>Justizgeschäften<\/mark>.&gt;3 § 2. &lt;Das Bezirksamt steht rücksichtlich des...","fid":"d138e126"},{"form":"Justizgeschäften","weight":"1","pos":3984,"context":"3Korrektur Thuns aus: Verwaltungs- und <mark>Justizgeschäften<\/mark>, die nicht ausdrücklich anderen Behörden oder Organen vorbehalten...","fid":"page"}]}]}