{"stem":"kanzleydirectialgeschäft","instances":[{"docId":"grundzuege-wirkungskreis-evangelische-konsistorialraete-1850-a3-xxi-d96","docUri":"grundzuege-wirkungskreis-evangelische-konsistorialraete-1850-a3-xxi-d96.html","score":1,"contexts":[{"form":"Kanzleydirectialgeschäfte","weight":"1","pos":122,"context":"...Rechnungen und Evidenzhaltung derselben. 6. Die Gremial- und <mark>Kanzleydirectialgeschäfte<\/mark>. 7. Streitigkeiten in den Religionsgemeinden selbst oder auch...","fid":"d228e82"}]}]}