{"stem":"mögten","instances":[{"docId":"entwuerfe-statut-universitaet-wien_1857_a3-xxi-d407","docUri":"entwuerfe-statut-universitaet-wien_1857_a3-xxi-d407.html","score":2,"contexts":[{"form":"mögten","weight":"1","pos":7168,"context":"...jeder einzelnen Stunde, die sie etwa genöthigt sein <mark>mögten<\/mark> ausfallen zu lassen, den Studiendirector in Kenntnis zu...","fid":"d134e2060"},{"form":"mögten","weight":"1","pos":15157,"context":"...jeder einzelnen Stunde, die sie etwa genöthigt sein <mark>mögten<\/mark> ausfallen zu lassen, den Studiendirector in Kenntnis zu...","fid":"d134e2060"}]}]}