{"stem":"nachstunden","instances":[{"docId":"entwurf-gesetz-volksschulen-od-a3-xxi-d651","docUri":"entwurf-gesetz-volksschulen-od-a3-xxi-d651.html","score":3,"contexts":[{"form":"Nachstunden","weight":"1","pos":3603,"context":"...den Schulstunden an einzelne oder alle Sch端ler gegen Entgeld <mark>Nachstunden<\/mark> zu geben. Er steht auch r端cksichtlich dieser Nachstunden...","fid":"d142e1375"},{"form":"Nachstunden","weight":"1","pos":3606,"context":"...Nachstunden zu geben. Er steht auch r端cksichtlich dieser <mark>Nachstunden<\/mark> unter Aufsicht seiner Vorgesetzten. Das Stundengeld darf eine...","fid":"d142e1375"},{"form":"Nachstunden","weight":"1","pos":3621,"context":"...welche ihm der Ortsseelsorger zuweist, unentgeldlich f端r die <mark>Nachstunden<\/mark> aufnehmen.","fid":"d142e1375"}]}]}