{"stem":"obenbezeichneten","instances":[{"docId":"vortrag-ozegovich-slowaken-1849-a3-xxi-d99","docUri":"vortrag-ozegovich-slowaken-1849-a3-xxi-d99.html","score":1,"contexts":[{"form":"obenbezeichneten","weight":"1","pos":1319,"context":"...Ungarns beabsichtigt erscheine, was doch dem Inhalte der <mark>obenbezeichneten<\/mark> §§ der Reichsverfassung selbst zuwiderlaufen würde. Allein wenn man...","fid":"d814e96"}]},{"docId":"deutsch-an-finanzministerium-1859-1859-04-14-a3-xxi-d502","docUri":"deutsch-an-finanzministerium-1859-1859-04-14-a3-xxi-d502.html","score":1,"contexts":[{"form":"obenbezeichneten","weight":"1","pos":643,"context":"...mit 5 % verzinst wird und die unter den <mark>obenbezeichneten<\/mark> Bedingungen dieselbe Beruhigung für sein Capital gewährt als die...","fid":"d106e117"}]}]}