{"stem":"onkel","instances":[{"docId":"zeithammer-an-thun-1853-07-08-a3-xxi-d212","docUri":"zeithammer-an-thun-1853-07-08-a3-xxi-d212.html","score":3,"contexts":[{"form":"Onkel","weight":"1","pos":478,"context":"...Ursache: Weil kein Gymnasium näher liegt und sein <mark>Onkel<\/mark> hier ihn unterstützt. 3. Parkos Anton, aus...","fid":"d859e237"},{"form":"Onkel","weight":"1","pos":655,"context":"...Anton, aus Chrast Ursache: wird hier vom <mark>Onkel<\/mark> unterstützt. 3. Kostocil Johann, aus Raudnitz [...","fid":"d859e404"},{"form":"Onkel","weight":"1","pos":700,"context":"...hat in der Nähe von Prag einen Pfarrer zum <mark>Onkel<\/mark>, der ihn leichter hier erhalten kann. Woctecka Emmanuel...","fid":"d859e440"}]},{"docId":"schreiner-an-helfert-1855-07-29-a3-xxi-d347","docUri":"schreiner-an-helfert-1855-07-29-a3-xxi-d347.html","score":1,"contexts":[{"form":"Onkel","weight":"1","pos":455,"context":"...Familien Frankreichs, einem Herzoge von Ahrenberg, dem <mark>Onkel<\/mark> Seiner Eminenz des Kardinals Fürsten von Schwarzenberg, einem...","fid":"d589e151"}]},{"docId":"brenner-an-haferl-1854-09-21-a3-xxi-d284","docUri":"brenner-an-haferl-1854-09-21-a3-xxi-d284.html","score":1,"contexts":[{"form":"Onkel","weight":"1","pos":106,"context":"...ihn nach Prag berufe. Als Auskunftsperson könne der <mark>Onkel<\/mark> von Kardinal Schwarzenberg, der Herzog von Arenberg,...","fid":"d80e55"}]},{"docId":"thun-franz-an-thun-1853-08-12-a3-xxi-d224","docUri":"thun-franz-an-thun-1853-08-12-a3-xxi-d224.html","score":1,"contexts":[{"form":"Onkel","weight":"1","pos":515,"context":"...den dem Dir bekannten reichen Giacomo Cis, seinem <mark>Onkel<\/mark>, zu einer vortheilhaften Heirath gedrängt, stets,...","fid":"d777e298"}]},{"docId":"thun-an-goluchowski-1859-07-29-a3-xxi-d514","docUri":"thun-an-goluchowski-1859-07-29-a3-xxi-d514.html","score":1,"contexts":[{"form":"Onkel","weight":"1","pos":975,"context":"...den Schicksalsschlägen für uns nicht ab) – bekanntlich ein <mark>Onkel<\/mark> der Gräfin Gol[uchowski] und Haustheolog des...","fid":"d705e241"}]}]}