{"stem":"pack","instances":[{"docId":"andriewicz-an-thun-1859-11-05-a3-xxi-d524","docUri":"andriewicz-an-thun-1859-11-05-a3-xxi-d524.html","score":1,"contexts":[{"form":"Pack","weight":"1","pos":563,"context":"...Oktober [1]858 dem k.k. Statthaltereisekretär Herrn Josefowicz ein <mark>Pack<\/mark> Banknoten im Amte anzubiethen sich unterfieng und für diese...","fid":"d16e115"}]},{"docId":"lehrerkollegium-gymnasium-graz-an-thun-1860-a3-xxi-d623a28","docUri":"lehrerkollegium-gymnasium-graz-an-thun-1860-a3-xxi-d623a28.html","score":1,"contexts":[{"form":"Pack","weight":"1","pos":142,"context":"...Weymayr Franz Silly Anton Skubic Dr. Eduard Trummer Mathias <mark>Pack<\/mark> Friedrich Boser Georg Kaas Raynald Kaschowitz Edm. Rieder...","fid":"d388e105"}]}]}