{"stem":"plaint","instances":[{"docId":"memoire-ueber-verhaeltnisse-in-polnischen-bezirken-von-haxthausen-1856-a3-xxi-d400","docUri":"memoire-ueber-verhaeltnisse-in-polnischen-bezirken-von-haxthausen-1856-a3-xxi-d400.html","score":2,"contexts":[{"form":"plainte","weight":"1","pos":2744,"context":"...ils n'ont jamais fourni jusqu'ici le moindre sujet de <mark>plainte<\/mark> ou de grief. Moi comme catholique je n'avais...","fid":"d431e381"},{"form":"plainte","weight":"1","pos":3362,"context":"...mais jusqu'ici il n'y a encore un mot de <mark>plainte<\/mark> contre eux. Il y a aussi des Jésuites...","fid":"d431e381"}]},{"docId":"pitra-an-thun-1860-09-04-a3-xxi-d608","docUri":"pitra-an-thun-1860-09-04-a3-xxi-d608.html","score":1,"contexts":[{"form":"plaintes","weight":"1","pos":1394,"context":"...au loin l'essor, peut aussi s'évanouir par quelques <mark>plaintes<\/mark> et d'odieux parallèles. De plus, une époque...","fid":"d516e119"}]}]}