{"stem":"projecten","instances":[{"docId":"maassen-an-thun-1857-01-12-a3-xxi-d404","docUri":"maassen-an-thun-1857-01-12-a3-xxi-d404.html","score":1,"contexts":[{"form":"Projecten","weight":"1","pos":519,"context":"...daß ich Hochdenselben, statt von Resultaten, von <mark>Projecten<\/mark> rede. Worauf es mir ankam, war nur,...","fid":"d411e116"}]},{"docId":"thun-franz-an-thun-1853-07-21-a3-xxi-d218","docUri":"thun-franz-an-thun-1853-07-21-a3-xxi-d218.html","score":1,"contexts":[{"form":"Projecten","weight":"1","pos":223,"context":"...ich komme dann wenigstens vollkommen instruirt und mit meinen <mark>Projecten<\/mark> ganz im Reinen zurück. Auch hoffe ich hier noch...","fid":"d775e124"}]}]}