{"stem":"rhédey","instances":[{"docId":"listperson","docUri":"listperson.html","score":2,"contexts":[{"form":"Rhédey","weight":"1","pos":8674,"context":"<mark>Rhédey<\/mark>","fid":"tocTable"},{"form":"Rhédey","weight":"1","pos":8679,"context":"<mark>Rhédey<\/mark> von Kis-Rhéde","fid":"tocTable"}]},{"docId":"geschichte-evangelische-kirche-oesterreich-von-kuzmany_1850_a3-xxi-d92","docUri":"geschichte-evangelische-kirche-oesterreich-von-kuzmany_1850_a3-xxi-d92.html","score":1,"contexts":[{"form":"Rhédey","weight":"1","pos":1453,"context":"...regieren wollen: dagegen stemmten sich die Geistlichen mit Graf <mark>Rhédey<\/mark> Ludw[ig] an der Spitze und klagten bei der...","fid":"d212e386"}]}]}