{"stem":"sanitätspolizei","instances":[{"docId":"entwurf-einrichtung-wirkungskreis-bezirksaemter_1852_a3-xxi-d85","docUri":"entwurf-einrichtung-wirkungskreis-bezirksaemter_1852_a3-xxi-d85.html","score":2,"contexts":[{"form":"Sanitätspolizei","weight":"1","pos":2051,"context":"...Abstellung des Bettels. § 44. In Betreff der <mark>Sanitätspolizei<\/mark> hat das Bezirksamt mit Beachtung der bestehenden Vorschriften und...","fid":"d138e543"},{"form":"Sanitätspolizei","weight":"1","pos":2087,"context":"...des aus ihrem Verbande ausgeschiedenen Besitzes in Angelegenheiten der <mark>Sanitätspolizei<\/mark> und der Krankenpflege, des Impfwesens und der Geburtshilfe...","fid":"d138e543"}]}]}