{"stem":"scandalo","instances":[{"docId":"borovich-an-viale-prela-1856-01-03-a3-xxi-d363","docUri":"borovich-an-viale-prela-1856-01-03-a3-xxi-d363.html","score":1,"contexts":[{"form":"scandalo","weight":"1","pos":432,"context":"...vilipeso, schernito e bersagliato in pubblico con gravissimo <mark>scandalo<\/mark> il carattere che mi rinveste, e ciò in...","fid":"d79e96"}]},{"docId":"debiasi-an-thun-1854-06-22-a3-xxi-d263","docUri":"debiasi-an-thun-1854-06-22-a3-xxi-d263.html","score":1,"contexts":[{"form":"scandalo","weight":"1","pos":1723,"context":"...trovavano a Innsbruck. Peggio poi fu, che con <mark>scandalo<\/mark>, e meraviglia di tutti i buoni la cosa...","fid":"d104e187"}]}]}