{"stem":"standesgemäß","instances":[{"docId":"simor-an-thun-1854-12-01-a3-xxi-d296d","docUri":"simor-an-thun-1854-12-01-a3-xxi-d296d.html","score":1,"contexts":[{"form":"standesgemäß","weight":"1","pos":677,"context":"...Rom bei der auch hier herrschenden Theuerung durchaus nicht <mark>standesgemäß<\/mark> leben. Das Opfer wäre unter zwei Bedingnissen zu...","fid":"d619e154"}]},{"docId":"segesser-an-thun-konzept-1856-11-ca","docUri":"segesser-an-thun-konzept-1856-11-ca.html","score":1,"contexts":[{"form":"standesgemäß","weight":"1","pos":57,"context":"...Mittel aufwenden müssen, um mit seiner Familie in Graz <mark>standesgemäß<\/mark> leben zu können.","fid":"d610e58"}]}]}