{"stem":"stiftsvorständ","instances":[{"docId":"mitterndorfer-an-thun-1852-04-15-a3-xxi-d163","docUri":"mitterndorfer-an-thun-1852-04-15-a3-xxi-d163.html","score":2,"contexts":[{"form":"Stiftsvorstände","weight":"1","pos":242,"context":"...Benediktiner Äbte, sondern nur als freie Wünsche einiger <mark>Stiftsvorstände<\/mark> betrachtet werden mögen, und daß ich die Drucklegung nicht...","fid":"d447e138"},{"form":"Stiftsvorstände","weight":"1","pos":629,"context":"...Wunde schlägt, wenn Euer Gnaden oder jeder der <mark>Stiftsvorstände<\/mark> an der von seinen Capitularen besetzten Lehranstalt, etwa...","fid":"d447e186"}]}]}