{"stem":"stockwerken","instances":[{"docId":"jaksch-an-thun-1856-03-23-a3-xxi-d373","docUri":"jaksch-an-thun-1856-03-23-a3-xxi-d373.html","score":2,"contexts":[{"form":"Stockwerken","weight":"1","pos":926,"context":"...nicht begegnen, weil die betreffenden Operationssäle in verschiedenen <mark>Stockwerken<\/mark> bestehen und ihren passenden Ort nirgends anderwärts finden können,...","fid":"d318e240"},{"form":"Stockwerken","weight":"1","pos":1406,"context":"...Hauptgebäudes mit Auflassung der dann überflüssigen Inspektionszimmer in den <mark>Stockwerken<\/mark> weiterhin verbleiben, und wenigstens auf den klinischen Sälen...","fid":"d318e240"}]}]}