{"stem":"szilagyi","instances":[{"docId":"listperson","docUri":"listperson.html","score":1,"contexts":[{"form":"Szilagyi","weight":"1","pos":10456,"context":"<mark>Szilagyi<\/mark>","fid":"tocTable"}]},{"docId":"heufler-an-thun-1850-07-12-a3-xxi-d61","docUri":"heufler-an-thun-1850-07-12-a3-xxi-d61.html","score":1,"contexts":[{"form":"Szilagyi","weight":"1","pos":378,"context":"...Winter hat er nämlich den Steuereinnehmer Andreas Szilagy [<mark>Szilagyi<\/mark>] in Zilah zum romanischen Schulrath vorgeschlagen. Obwohl...","fid":"d285e130"}]}]}