{"stem":"südtyrol","instances":[{"docId":"notizen-thun-sprachenfrage-gerichte_1859_a3-xxi-d525g","docUri":"notizen-thun-sprachenfrage-gerichte_1859_a3-xxi-d525g.html","score":1,"contexts":[{"form":"Südtyrol","weight":"1","pos":82,"context":"...Gerichte deutsch - nur in Dalmazien, Venezien, <mark>Südtyrol<\/mark> ganz, dann in Istrien großentheils italienisch im äußeren Dienste...","fid":"d483e80"}]},{"docId":"notizen-thun-sprachenfrage-gerichte_1859_a3-xxi-d525","docUri":"notizen-thun-sprachenfrage-gerichte_1859_a3-xxi-d525.html","score":1,"contexts":[{"form":"Südtyrol","weight":"1","pos":160,"context":"...Gerichte deutsch – nur in Dalmazien, Venezien, <mark>Südtyrol<\/mark> ganz, dann in Istrien großentheils italienisch im äußeren Dienste...","fid":"d482e122"}]}]}