{"stem":"ton","instances":[{"docId":"diepenbrock-an-thun_1850-05-06_a3-xxi-d50","docUri":"diepenbrock-an-thun_1850-05-06_a3-xxi-d50.html","score":1,"contexts":[{"form":"Ton","weight":"1","pos":226,"context":"...als daß ich genau und sicher ermessen könnte, welcher <mark>Ton<\/mark> in dieser Sache, diesen Stimmen gegenüber, als der rechte...","fid":"d114e132"}]},{"docId":"jarcke-an-thun-1852-08-07-a3-xxi-d171","docUri":"jarcke-an-thun-1852-08-07-a3-xxi-d171.html","score":1,"contexts":[{"form":"Ton","weight":"1","pos":1647,"context":"...und nicht minder schwer dürfte es sein den herrschenden <mark>Ton<\/mark> und Geist einer enggeschlossenen Cooperation, wie der österreichische...","fid":"d323e189"}]},{"docId":"flir-an-thun-1858-07-29-a3-xxi-d462","docUri":"flir-an-thun-1858-07-29-a3-xxi-d462.html","score":1,"contexts":[{"form":"Ton","weight":"1","pos":566,"context":"...gute Gründe, dieses zuversichtig zu erwarten.“ Dieser <mark>Ton<\/mark> schüchterte die Herren ein. Wenn – und dieses erlaube...","fid":"d191e121"}]},{"docId":"kleemann-an-thun-1858-06-23-a3-xxi-d456","docUri":"kleemann-an-thun-1858-06-23-a3-xxi-d456.html","score":1,"contexts":[{"form":"Ton","weight":"1","pos":2017,"context":"...sich ferner in den Provinzen die Ansicht, daß <mark>Ton<\/mark> und Inhalt jener Artikel im Sinne und nach Wunsch...","fid":"d359e286"}]},{"docId":"ficker-an-thun-1858-06-15-a3-xxi-d453","docUri":"ficker-an-thun-1858-06-15-a3-xxi-d453.html","score":1,"contexts":[{"form":"Ton","weight":"1","pos":913,"context":"...rechtfertigen könnte, da es natürlich, was auch der ganze <mark>Ton<\/mark> der Recension nicht gestattet, lächerlich wäre, anzunehmen,...","fid":"d177e173"}]},{"docId":"beck-an-thun-1853-05-18-a3-xxi-d205","docUri":"beck-an-thun-1853-05-18-a3-xxi-d205.html","score":1,"contexts":[{"form":"Ton","weight":"1","pos":778,"context":"...zu haben, wenn aus einem verstimmten Instrument ein schriller <mark>Ton<\/mark> hie und da das Ohr verletzt. Als Fürsprecher...","fid":"d39e118"}]},{"docId":"moy-an-thun-1854-12-08-a3-xxi-d308","docUri":"moy-an-thun-1854-12-08-a3-xxi-d308.html","score":1,"contexts":[{"form":"Ton","weight":"1","pos":83,"context":"..., so Moy weiter, sei in einem äußerst erniedrigenden <mark>Ton<\/mark> gehalten, und wolle das Verhalten der Professoren bei...","fid":"d456e55"}]},{"docId":"helfert-an-thun-1850-11-a3-xxi-d77","docUri":"helfert-an-thun-1850-11-a3-xxi-d77.html","score":1,"contexts":[{"form":"Ton","weight":"1","pos":1176,"context":"...von nationaler Seite und in nationaler Sprache ein anderer <mark>Ton<\/mark> überhaupt nicht angestimmt worden ist; denn leider sind die...","fid":"d273e215"}]}]}