{"stem":"trunkenheit","instances":[{"docId":"bezirkskommissariate-an-stadthauptmannschaft-1851-03-a3-xxi-d109","docUri":"bezirkskommissariate-an-stadthauptmannschaft-1851-03-a3-xxi-d109.html","score":1,"contexts":[{"form":"Trunkenheit","weight":"1","pos":1094,"context":"...inne hat, dessen Geist aber durch eingewurzelten Hang zur <mark>Trunkenheit<\/mark> stumpf geworden ist, daher mit dem gegenw채rtigen Bed체rfnisse der...","fid":"d61e329"}]},{"docId":"godeassi-an-viale-prela-1856-02-22-a3-xxi-d401","docUri":"godeassi-an-viale-prela-1856-02-22-a3-xxi-d401.html","score":1,"contexts":[{"form":"Trunkenheit","weight":"1","pos":160,"context":"...Verhaftung. Zun채chst betont er, dass Borovich f체r seine <mark>Trunkenheit<\/mark> und Gewaltbereitschaft bekannt gewesen sei. Er selbst habe ihn...","fid":"d219e55"}]}]}