{"stem":"untauglichkeit","instances":[{"docId":"entwurf-wirkungskreis-ministerium-fuer-kultus-und-unterricht-o-d-a3-xxi-d84","docUri":"entwurf-wirkungskreis-ministerium-fuer-kultus-und-unterricht-o-d-a3-xxi-d84.html","score":2,"contexts":[{"form":"Untauglichkeit","weight":"1","pos":1073,"context":"...Die Bewilligung von Defizientengehalten für Seelsorger, wenn ihre <mark>Untauglichkeit<\/mark> zur Verrichtung der Seelsorge und ihre Vermögenslosigkeit strenge erwiesen...","fid":"d158e458"},{"form":"Untauglichkeit","weight":"1","pos":1103,"context":"...Die Bewilligung von Defizientengehalten für Seelsorger, wenn ihre <mark>Untauglichkeit<\/mark> zur Verrichtung der Seelsorge und ihre Vermögenslosigkeit strenge erwiesen...","fid":"d158e458"}]}]}