{"stem":"verdrehten","instances":[{"docId":"winaricky-an-thun-1860-07-08-a3-xxi-d596","docUri":"winaricky-an-thun-1860-07-08-a3-xxi-d596.html","score":1,"contexts":[{"form":"verdrehten","weight":"1","pos":425,"context":"...verhüten – mit Licht und Schatten. Verkannten und <mark>verdrehten<\/mark> die nun wieder tonangebenden Alldeutschthümler seine allseits versöhnende Tendenz...","fid":"d843e117"}]},{"docId":"thun-an-goluchowski-1859-07-29-a3-xxi-d514","docUri":"thun-an-goluchowski-1859-07-29-a3-xxi-d514.html","score":1,"contexts":[{"form":"verdrehten","weight":"1","pos":561,"context":"..., daß Hinneigung nach Rußland – abgesehen von einzelnen <mark>verdrehten<\/mark> Köpfen, deren es überall gibt – anders als...","fid":"d705e163"}]}]}