{"stem":"virgini","instances":[{"docId":"ueberblick-entwicklung-evangelisches-kirchenrecht-oesterreich-o-d-a3-xxi-d93","docUri":"ueberblick-entwicklung-evangelisches-kirchenrecht-oesterreich-o-d-a3-xxi-d93.html","score":1,"contexts":[{"form":"virginis","weight":"1","pos":884,"context":"...! factioni] ipsi adhaerentes tamquam haereticos hostesque sacratissimae <mark>virginis<\/mark> Mariae poena capitis et ablatione omnium bonorum majestas regia...","fid":"d796e466"}]},{"docId":"dittrich-an-thun-1849-09-05-a3-xxi-d6","docUri":"dittrich-an-thun-1849-09-05-a3-xxi-d6.html","score":1,"contexts":[{"form":"Virginis","weight":"1","pos":353,"context":"...um die freie Meinung der immaculata conceptione Beatae Mariae <mark>Virginis<\/mark> zu einem Lehrsatze oder Dogma der katholischen Kirche zu...","fid":"d119e129"}]}]}