{"stem":"voix","instances":[{"docId":"apponyi-therese-an-thun-1858-08-14-a3-xxi-d466","docUri":"apponyi-therese-an-thun-1858-08-14-a3-xxi-d466.html","score":2,"contexts":[{"form":"voix","weight":"1","pos":213,"context":"...forte au cœur, et j'ose humblement unir ma <mark>voix<\/mark> à la sienne en demandant votre haute protection en...","fid":"d27e118"},{"form":"voix","weight":"1","pos":276,"context":"..., pour moi, mais je ne suis qu'une <mark>voix<\/mark> de plus, qui se permet de placer son...","fid":"d27e118"}]},{"docId":"pitra-an-thun-1860-09-04-a3-xxi-d608","docUri":"pitra-an-thun-1860-09-04-a3-xxi-d608.html","score":1,"contexts":[{"form":"voix","weight":"1","pos":568,"context":"...seizième siècle, peu après que l'orient à la <mark>voix<\/mark> de S. François Xavier se fut ouvert à l'autre...","fid":"d516e119"}]},{"docId":"memoire-ueber-verhaeltnisse-in-polnischen-bezirken-von-haxthausen-1856-a3-xxi-d400","docUri":"memoire-ueber-verhaeltnisse-in-polnischen-bezirken-von-haxthausen-1856-a3-xxi-d400.html","score":1,"contexts":[{"form":"voix","weight":"1","pos":3898,"context":"...qui s'avisera de débiter par écrit ou de vive <mark>voix<\/mark> des maximes contraires à la sécurité de l'Etat,...","fid":"d431e381"}]}]}