{"stem":"vouloir","instances":[{"docId":"skrzynecki-an-thun_1850-03-30_a3-xxi-d38","docUri":"skrzynecki-an-thun_1850-03-30_a3-xxi-d38.html","score":2,"contexts":[{"form":"vouloir","weight":"1","pos":128,"context":"...vous exposer ma demande, je vous prie de <mark>vouloir<\/mark> lire les motifs qui m'y déterminent. A la...","fid":"d627e112"},{"form":"vouloir","weight":"1","pos":337,"context":"...vous, en vous prirant [priant] de <mark>vouloir<\/mark> intercéder en ma faveur auprès de S. Altesse le...","fid":"d627e112"}]},{"docId":"pitra-an-thun-1860-09-04-a3-xxi-d608","docUri":"pitra-an-thun-1860-09-04-a3-xxi-d608.html","score":1,"contexts":[{"form":"vouloir","weight":"1","pos":909,"context":"...métropoles. Loin de moi la pensée ni de <mark>vouloir<\/mark> disputer les droits acquis, ni d'envier le faste...","fid":"d516e119"}]},{"docId":"pitra-an-thun-1860-09-12-a3-xxi-d608a","docUri":"pitra-an-thun-1860-09-12-a3-xxi-d608a.html","score":1,"contexts":[{"form":"vouloir","weight":"1","pos":357,"context":"...à m'en occuper. Je prie Votre Excellence de <mark>vouloir<\/mark> bien considérer ceci et tout ce que j'ai eu...","fid":"d517e120"}]},{"docId":"melloni-an-littrow-1854-a3-xxi-d314","docUri":"melloni-an-littrow-1854-a3-xxi-d314.html","score":1,"contexts":[{"form":"vouloir","weight":"1","pos":422,"context":"...emploi et honoraires sans me dire pourquoi et sans <mark>vouloir<\/mark> même insérer ma destitution, et celle de la...","fid":"d430e112"}]},{"docId":"thun-an-de-luca-02-01-ca642","docUri":"thun-an-de-luca-02-01-ca642.html","score":1,"contexts":[{"form":"vouloir","weight":"1","pos":47,"context":"J'ose prier Votre Excellence de bien <mark>vouloir<\/mark> lire le document ci-joint, et me faire...","fid":"d680e111"}]},{"docId":"villermont-an-thun-1860-08-08-a3-xxi-d600","docUri":"villermont-an-thun-1860-08-08-a3-xxi-d600.html","score":1,"contexts":[{"form":"vouloir","weight":"1","pos":553,"context":"...l'honneur de vous adresser et de vous prier de <mark>vouloir<\/mark> bien agréer l'hommage de l'expression profondément respectueux, avec...","fid":"d806e188"}]}]}