{"stem":"voulez","instances":[{"docId":"toqueville-an-thun-1856-03-13-a3-xxi-d371","docUri":"toqueville-an-thun-1856-03-13-a3-xxi-d371.html","score":2,"contexts":[{"form":"voulez","weight":"1","pos":156,"context":"...connaissance et j'espère qu'en mémoire de son oncle vous <mark>voulez<\/mark> bien le revoir avec un peu d'amitié, ce...","fid":"d793e110"},{"form":"voulez","weight":"1","pos":173,"context":"..., très digne de toutes les bontés que vous <mark>voulez<\/mark> bien avoir pour lui. Je suis charmé d'avoir...","fid":"d793e110"}]}]}