{"stem":"vykázané","instances":[{"docId":"amerling-an-thun-1853-07-20-a3-xxi-d217","docUri":"amerling-an-thun-1853-07-20-a3-xxi-d217.html","score":1,"contexts":[{"form":"vykázané","weight":"1","pos":277,"context":"...když do Prahy přijeti račíte, aneb k tomu <mark>vykázané<\/mark> komisí složené ze znalců učitelských jak duchovních tak i...","fid":"d15e118"}]},{"docId":"rojek-an-thun-1854-11-14-a3-xxi-d302","docUri":"rojek-an-thun-1854-11-14-a3-xxi-d302.html","score":1,"contexts":[{"form":"vykázané","weight":"1","pos":3088,"context":"...přeje lhůtu poznání a obracení se na cesty Bohem <mark>vykázané<\/mark>. A této lhůty nám dané v celé míře...","fid":"d570e166"}]}]}