{"stem":"vyznává","instances":[{"docId":"rojek-an-thun-1854-11-14-a3-xxi-d302","docUri":"rojek-an-thun-1854-11-14-a3-xxi-d302.html","score":2,"contexts":[{"form":"vyznává","weight":"1","pos":1885,"context":"...při drahé oběti mešní – ale tu víru svou <mark>vyznává<\/mark> i před zástupy synů světa. Příkladem z mnohých...","fid":"d570e166"},{"form":"vyznává","weight":"1","pos":2000,"context":"...Syna Božího, přítomného v svátosti. – Tak <mark>vyznává<\/mark> Krista a dává Bohu co Božího jest i před...","fid":"d570e166"}]}]}