{"stem":"zehrt","instances":[{"docId":"entwuerfe-statut-universitaet-wien_1857_a3-xxi-d407","docUri":"entwuerfe-statut-universitaet-wien_1857_a3-xxi-d407.html","score":2,"contexts":[{"form":"zehrt","weight":"1","pos":6839,"context":"...dazu irgend etwas beizutragen, vom Marke der Universität <mark>zehrt<\/mark>. Der Erfinder der Phrase wollte offenbar nach zwei...","fid":"d134e1988"},{"form":"zehrt","weight":"1","pos":14828,"context":"...dazu irgend etwas beizutragen, vom Marke der Universität <mark>zehrt<\/mark>. Der Erfinder der Phrase wollte offenbar nach zwei...","fid":"d134e1988"}]}]}