{"stem":"zustellungen","instances":[{"docId":"safarik-an-thun-1853-02-27-a3-xxi-d192","docUri":"safarik-an-thun-1853-02-27-a3-xxi-d192.html","score":1,"contexts":[{"form":"Zustellungen","weight":"1","pos":1172,"context":"...Auch standen bisher die Beamtenwohnungen zu jeder Zeit den <mark>Zustellungen<\/mark> der k.k. Post, der Behörden, der Buchhändler...","fid":"d575e236"}]},{"docId":"note-nadasdy-an-goluchowski-1859-11-05-a3-xxi-d525b","docUri":"note-nadasdy-an-goluchowski-1859-11-05-a3-xxi-d525b.html","score":1,"contexts":[{"form":"Zustellungen","weight":"1","pos":1772,"context":"...übrigens für den Eperieser Sprengel angeordnet, daß bei <mark>Zustellungen<\/mark> von Klagen, worüber eine Tagsatzung angeordnet wird oder...","fid":"d473e156"}]}]}