{"stem":"überflügelt","instances":[{"docId":"memorandum-parteiverhaeltnisse-ungarn-od-a3-xxi-d645","docUri":"memorandum-parteiverhaeltnisse-ungarn-od-a3-xxi-d645.html","score":1,"contexts":[{"form":"überflügelt","weight":"1","pos":1168,"context":"...mit Grund voraussagen, daß die altkonservative Parthei vollständig <mark>überflügelt<\/mark> und ein dem Jahre 1848 analoger Verlauf und Ausgang...","fid":"d439e81"}]},{"docId":"thun-ueber-ungarischen-verhaeltnisse_1859-11_a3-xxi-d527","docUri":"thun-ueber-ungarischen-verhaeltnisse_1859-11_a3-xxi-d527.html","score":1,"contexts":[{"form":"überflügelt","weight":"1","pos":1421,"context":"...ihnen immer mehr aufdrängenden Befürchtung, sonst im Lande <mark>überflügelt<\/mark> zu werden. Je mehr sie aber jetzt unter dem...","fid":"d783e274"}]}]}